MyHeartCounts/__init__.py
MyHeartCounts/demo.py
MyHeartCounts/download_mindsetdata.py
MyHeartCounts/download_minsetdata.py
MyHeartCounts/myHeartCounts.py
MyHeartCounts/study/Study.py
MyHeartCounts/study/__init__.py
MyHeartCounts/user/User.py
MyHeartCounts/user/__init__.py
MyHeartCounts-0.0.22.dist-info/LICENSE.md
MyHeartCounts-0.0.22.dist-info/METADATA
MyHeartCounts-0.0.22.dist-info/WHEEL
MyHeartCounts-0.0.22.dist-info/top_level.txt
MyHeartCounts-0.0.22.dist-info/zip-safe
MyHeartCounts-0.0.22.dist-info/RECORD
