Metadata-Version: 2.1
Name: MyHeartCounts
Version: 0.0.22
Summary: Python wrapper to load and analyze studies on My Heart Counts App
Home-page: https://github.com/AshleyLab/MyHeartCounts2.0
Author: A. Javed
Author-email: alijaved@live.com
License: UNKNOWN
Download-URL: https://github.com/AshleyLab/MyHeartCounts2.0/archive/refs/tags/v0.0.22.tar.gz
Platform: UNKNOWN
License-File: LICENSE.md
Requires-Dist: numpy
Requires-Dist: synapseclient
Requires-Dist: datetime
Requires-Dist: pandas
